LICENSE.txt
MANIFEST.in
README.rst
setup.py
gtw/__init__.py
gtw/auth.py
gtw/base.py
gtw/error.py
gtw/mixins.py
gtw/organizer.py
gtw/registrant.py
gtw/session.py
gtw/webinar.py
gtw/test/__init__.py
gtw/test/helper.py
gtw/test/organizer_jukebox.py
gtw/test/test_organizer.py
gtw/test/test_registrant.py
gtw/test/test_session.py
gtw/test/test_webinar.py
gtwpy.egg-info/PKG-INFO
gtwpy.egg-info/SOURCES.txt
gtwpy.egg-info/dependency_links.txt
gtwpy.egg-info/requires.txt
gtwpy.egg-info/top_level.txt