Metadata-Version: 1.0
Name: gtwpy
Version: 1.3.10
Summary: A kickass wrapper around the Citrix GoToWebinar REST API
Home-page: https://github.com/HubSpot/gtwpy
Author: prior
Author-email: mprior@hubspot.com
License: LICENSE.txt
Download-URL: https://github.com/HubSpot/gtwpy/tarball/v1.3.10
Platform: any
